spider_admin_pro/__init__.py
spider_admin_pro/api_result.py
spider_admin_pro/compat.py
spider_admin_pro/logger.py
spider_admin_pro/main.py
spider_admin_pro/router.py
spider_admin_pro/version.py
spider_admin_pro/api/__init__.py
spider_admin_pro/api/action_history_api.py
spider_admin_pro/api/auth_api.py
spider_admin_pro/api/schedule_api.py
spider_admin_pro/api/scrapyd_api.py
spider_admin_pro/api/scrapyd_server_api.py
spider_admin_pro/api/stats_collection_api.py
spider_admin_pro/api/system_info_api.py
spider_admin_pro/config/__init__.py
spider_admin_pro/config/default_config.py
spider_admin_pro/config/yaml_config.py
spider_admin_pro/enums/__init__.py
spider_admin_pro/enums/schedule_type_enum.py
spider_admin_pro/exceptions/__init__.py
spider_admin_pro/exceptions/api_exception.py
spider_admin_pro/exceptions/constant.py
spider_admin_pro/model/__init__.py
spider_admin_pro/model/base.py
spider_admin_pro/model/login_history_model.py
spider_admin_pro/model/schedule_history_model.py
spider_admin_pro/model/scrapyd_server_model.py
spider_admin_pro/model/stats_collection_model.py
spider_admin_pro/public/index.html
spider_admin_pro/public/static/favicon.ico
spider_admin_pro/public/static/css/app.abba2b4a.css
spider_admin_pro/public/static/css/chunk-0ccfecea.db0d5879.css
spider_admin_pro/public/static/css/chunk-1ecb2d7e.e3ee4235.css
spider_admin_pro/public/static/css/chunk-23c8897f.e3ee4235.css
spider_admin_pro/public/static/css/chunk-3abab049.3c7f5ad9.css
spider_admin_pro/public/static/css/chunk-3d8f8b15.e3ee4235.css
spider_admin_pro/public/static/css/chunk-6b332efd.e3ee4235.css
spider_admin_pro/public/static/css/chunk-7283689f.014db34f.css
spider_admin_pro/public/static/css/chunk-8b2a2660.33ebb8c7.css
spider_admin_pro/public/static/css/chunk-92f62286.c5998641.css
spider_admin_pro/public/static/css/chunk-elementUI.8fc3034b.css
spider_admin_pro/public/static/css/chunk-libs.3dfb7769.css
spider_admin_pro/public/static/fonts/element-icons.535877f5.woff
spider_admin_pro-3.0.9.dist-info/LICENSE
spider_admin_pro-3.0.9.dist-info/METADATA
spider_admin_pro-3.0.9.dist-info/WHEEL
spider_admin_pro-3.0.9.dist-info/top_level.txt
spider_admin_pro-3.0.9.dist-info/zip-safe
spider_admin_pro-3.0.9.dist-info/RECORD
