Metadata-Version: 2.1
Name: spider-admin-pro
Version: 3.0.9
Summary: a spider admin based vue, scrapyd api and APScheduler
Home-page: https://github.com/mouday/spider-admin-pro
Author: Peng Shiyu
Author-email: pengshiyuyx@gmail.com
License: MIT
Keywords: spider admin scrapy scrapyd scheduler
Classifier: Development Status :: 5 - Production/Stable
Classifier: Intended Audience :: Developers
Classifier: License :: OSI Approved :: MIT License
Classifier: Operating System :: OS Independent
Classifier: Programming Language :: Python
Classifier: Programming Language :: Python :: 2
Classifier: Programming Language :: Python :: 2.7
Classifier: Programming Language :: Python :: 3
Classifier: Programming Language :: Python :: 3.4
Classifier: Programming Language :: Python :: 3.5
Classifier: Programming Language :: Python :: 3.6
Classifier: Programming Language :: Python :: 3.7
Classifier: Programming Language :: Python :: 3.8
Classifier: Programming Language :: Python :: 3.9
Classifier: Programming Language :: Python :: 3.10
Classifier: Programming Language :: Python :: 3.11
Classifier: Programming Language :: Python :: 3.12
Classifier: Topic :: Internet :: WWW/HTTP :: Dynamic Content
Classifier: Topic :: Internet :: WWW/HTTP :: WSGI :: Application
Classifier: Topic :: Software Development :: Libraries :: Application Frameworks
Classifier: Topic :: Software Development :: Libraries :: Python Modules
License-File: LICENSE
Requires-Dist: six
Requires-Dist: APScheduler
Requires-Dist: environs
Requires-Dist: Flask
Requires-Dist: Flask-Cors
Requires-Dist: ip-area
Requires-Dist: peewee
Requires-Dist: psutil
Requires-Dist: PyJWT
Requires-Dist: python-dotenv
Requires-Dist: PyYAML
Requires-Dist: requests
Requires-Dist: scrapyd-api
Requires-Dist: session-request
Requires-Dist: SQLAlchemy
Requires-Dist: ua-parser
Requires-Dist: user-agents
Requires-Dist: Werkzeug
Requires-Dist: gunicorn
Requires-Dist: flask-compress
Requires-Dist: whitenoise
